cdpam/__init__.py
cdpam/cdpam.py
cdpam/models.py
cdpam/CDPAM_trained/scratchJNDdefault_best_model.pth
cdpam-0.0.6.dist-info/METADATA
cdpam-0.0.6.dist-info/WHEEL
cdpam-0.0.6.dist-info/top_level.txt
cdpam-0.0.6.dist-info/RECORD
